fpga_device_manager/Config.py
fpga_device_manager/Constants.py
fpga_device_manager/Devices.py
fpga_device_manager/Inputs.py
fpga_device_manager/Pins.py
fpga_device_manager/Popup.py
fpga_device_manager/Preview.py
fpga_device_manager/__init__.py
fpga_device_manager/__main__.py
fpga_device_manager/device_base.py
fpga_device_manager/device_manager.py
fpga_device_manager/device_params.py
fpga_device_manager/exceptions.py
fpga_device_manager/qt-preview.py
fpga_device_manager/generator/__init__.py
fpga_device_manager/generator/__main__.py
fpga_device_manager/res/data/device_types.json
fpga_device_manager/res/data/input_types.json
fpga_device_manager/res/data/pins.json
fpga_device_manager/res/fonts/libsans-bold.ttf
fpga_device_manager/res/fonts/libsans.ttf
fpga_device_manager/res/ui/device.ui
fpga_device_manager/res/ui/device_assoc.ui
fpga_device_manager/res/ui/device_list.ui
fpga_device_manager/res/ui/device_pin.ui
fpga_device_manager/res/ui/device_settings.ui
fpga_device_manager/res/ui/label_slider.ui
fpga_device_manager/res/ui/main.ui
fpga_device_manager/res/vtemplates/base.tpl
fpga_device_manager/res/vtemplates/devices_in.v.tpl
fpga_device_manager/res/vtemplates/devices_out.v.tpl
fpga_device_manager/res/vtemplates/pins_in.v.tpl
fpga_device_manager/res/vtemplates/pins_out.v.tpl
fpga_device_manager/res/vtemplates/smarthome.ldf.tpl
fpga_device_manager/res/vtemplates/types.v.tpl
fpga_device_manager/res/vtemplates/types_out.v.tpl
fpga_device_manager/widgets/__init__.py
fpga_device_manager/widgets/colorbutton.py
fpga_device_manager/widgets/device_assoc.py
fpga_device_manager/widgets/device_list.py
fpga_device_manager/widgets/device_pin.py
fpga_device_manager/widgets/device_widget.py
fpga_device_manager/widgets/percent_slider.py
fpga_device_manager/widgets/preview.py
fpga_device_manager/widgets/state_spinbox.py
fpga_device_manager/windows/__init__.py
fpga_device_manager/windows/base.py
fpga_device_manager/windows/device_settings.py
fpga_device_manager/windows/main_window.py
fpga_device_manager-0.2.4.dist-info/LICENSE
fpga_device_manager-0.2.4.dist-info/METADATA
fpga_device_manager-0.2.4.dist-info/WHEEL
fpga_device_manager-0.2.4.dist-info/top_level.txt
fpga_device_manager-0.2.4.dist-info/RECORD
