Metadata-Version: 2.1
Name: fpga-device-manager
Version: 0.2.4
Summary: A GUI for managing FPGA Device configurations.
Home-page: UNKNOWN
Author: Hannes Preiss
Author-email: sophie@sophieware.net
License: MIT
Platform: UNKNOWN
Classifier: Development Status :: 3 - Alpha
Classifier: Programming Language :: Python :: 3
Classifier: License :: OSI Approved :: MIT License
Classifier: Operating System :: OS Independent
Requires-Python: >=3.7
Requires-Dist: moody-templates
Requires-Dist: PySide2
Requires-Dist: QtPy
